[
  {
    "ContainingType": "DiemDanhLopHoc.Controllers.AuthController",
    "Method": "ChangePassword",
    "RelativePath": "api/Auth/change-password",
    "HttpMethod": "POST",
    "IsController": true,
    "Order": 0,
    "Parameters": [
      {
        "Name": "request",
        "Type": "DiemDanhLopHoc.DTOs.ChangePasswordDto",
        "IsRequired": true
      }
    ],
    "ReturnTypes": []
  },
  {
    "ContainingType": "DiemDanhLopHoc.Controllers.AuthController",
    "Method": "Login",
    "RelativePath": "api/Auth/login",
    "HttpMethod": "POST",
    "IsController": true,
    "Order": 0,
    "Parameters": [
      {
        "Name": "request",
        "Type": "DiemDanhLopHoc.DTOs.LoginRequestDto",
        "IsRequired": true
      }
    ],
    "ReturnTypes": []
  },
  {
    "ContainingType": "DiemDanhLopHoc.Controllers.BuoiHocController",
    "Method": "Create",
    "RelativePath": "api/BuoiHoc",
    "HttpMethod": "POST",
    "IsController": true,
    "Order": 0,
    "Parameters": [
      {
        "Name": "request",
        "Type": "DiemDanhLopHoc.DTOs.TaoBuoiHocDto",
        "IsRequired": true
      }
    ],
    "ReturnTypes": []
  },
  {
    "ContainingType": "DiemDanhLopHoc.Controllers.BuoiHocController",
    "Method": "GetById",
    "RelativePath": "api/BuoiHoc/{id}",
    "HttpMethod": "GET",
    "IsController": true,
    "Order": 0,
    "Parameters": [
      {
        "Name": "id",
        "Type": "System.Int32",
        "IsRequired": true
      }
    ],
    "ReturnTypes": []
  },
  {
    "ContainingType": "DiemDanhLopHoc.Controllers.BuoiHocController",
    "Method": "Delete",
    "RelativePath": "api/BuoiHoc/{id}",
    "HttpMethod": "DELETE",
    "IsController": true,
    "Order": 0,
    "Parameters": [
      {
        "Name": "id",
        "Type": "System.Int32",
        "IsRequired": true
      }
    ],
    "ReturnTypes": []
  },
  {
    "ContainingType": "DiemDanhLopHoc.Controllers.BuoiHocController",
    "Method": "GetByClassId",
    "RelativePath": "api/BuoiHoc/class/{maLop}",
    "HttpMethod": "GET",
    "IsController": true,
    "Order": 0,
    "Parameters": [
      {
        "Name": "maLop",
        "Type": "System.String",
        "IsRequired": true
      }
    ],
    "ReturnTypes": []
  },
  {
    "ContainingType": "DiemDanhLopHoc.Controllers.DiemDanhController",
    "Method": "BulkUpdate",
    "RelativePath": "api/DiemDanh/bulk-update",
    "HttpMethod": "POST",
    "IsController": true,
    "Order": 0,
    "Parameters": [
      {
        "Name": "requests",
        "Type": "System.Collections.Generic.List\u00601[[DiemDanhLopHoc.DTOs.DiemDanhDto, DiemDanhLopHoc, Version=1.0.0.0, Culture=neutral, PublicKeyToken=null]]",
        "IsRequired": true
      }
    ],
    "ReturnTypes": []
  },
  {
    "ContainingType": "DiemDanhLopHoc.Controllers.DiemDanhController",
    "Method": "GetLecturerStats",
    "RelativePath": "api/DiemDanh/lecturer-stats/{maGv}",
    "HttpMethod": "GET",
    "IsController": true,
    "Order": 0,
    "Parameters": [
      {
        "Name": "maGv",
        "Type": "System.String",
        "IsRequired": true
      }
    ],
    "ReturnTypes": []
  },
  {
    "ContainingType": "DiemDanhLopHoc.Controllers.DiemDanhController",
    "Method": "GetSessionAttendance",
    "RelativePath": "api/DiemDanh/session/{maBuoiHoc}",
    "HttpMethod": "GET",
    "IsController": true,
    "Order": 0,
    "Parameters": [
      {
        "Name": "maBuoiHoc",
        "Type": "System.Int32",
        "IsRequired": true
      }
    ],
    "ReturnTypes": []
  },
  {
    "ContainingType": "DiemDanhLopHoc.Controllers.DiemDanhController",
    "Method": "GetStudentAttendance",
    "RelativePath": "api/DiemDanh/student/{maSv}",
    "HttpMethod": "GET",
    "IsController": true,
    "Order": 0,
    "Parameters": [
      {
        "Name": "maSv",
        "Type": "System.String",
        "IsRequired": true
      }
    ],
    "ReturnTypes": []
  },
  {
    "ContainingType": "DiemDanhLopHoc.Controllers.DiemDanhController",
    "Method": "Submit",
    "RelativePath": "api/DiemDanh/submit",
    "HttpMethod": "POST",
    "IsController": true,
    "Order": 0,
    "Parameters": [
      {
        "Name": "request",
        "Type": "DiemDanhLopHoc.DTOs.SubmitDiemDanhDto",
        "IsRequired": true
      }
    ],
    "ReturnTypes": []
  },
  {
    "ContainingType": "DiemDanhLopHoc.Controllers.GiangVienController",
    "Method": "GetAll",
    "RelativePath": "api/giangvien",
    "HttpMethod": "GET",
    "IsController": true,
    "Order": 0,
    "Parameters": [],
    "ReturnTypes": []
  },
  {
    "ContainingType": "DiemDanhLopHoc.Controllers.GiangVienController",
    "Method": "Create",
    "RelativePath": "api/giangvien",
    "HttpMethod": "POST",
    "IsController": true,
    "Order": 0,
    "Parameters": [
      {
        "Name": "request",
        "Type": "DiemDanhLopHoc.DTOs.TaoGiangVienDto",
        "IsRequired": true
      }
    ],
    "ReturnTypes": []
  },
  {
    "ContainingType": "DiemDanhLopHoc.Controllers.GiangVienController",
    "Method": "Update",
    "RelativePath": "api/giangvien/{maGv}",
    "HttpMethod": "PUT",
    "IsController": true,
    "Order": 0,
    "Parameters": [
      {
        "Name": "maGv",
        "Type": "System.String",
        "IsRequired": true
      },
      {
        "Name": "request",
        "Type": "DiemDanhLopHoc.DTOs.CapNhatGiangVienDto",
        "IsRequired": true
      }
    ],
    "ReturnTypes": []
  },
  {
    "ContainingType": "DiemDanhLopHoc.Controllers.GiangVienController",
    "Method": "Delete",
    "RelativePath": "api/giangvien/{maGv}",
    "HttpMethod": "DELETE",
    "IsController": true,
    "Order": 0,
    "Parameters": [
      {
        "Name": "maGv",
        "Type": "System.String",
        "IsRequired": true
      }
    ],
    "ReturnTypes": []
  },
  {
    "ContainingType": "DiemDanhLopHoc.Controllers.GiangVienController",
    "Method": "ResetDevice",
    "RelativePath": "api/giangvien/{maSv}/reset-device",
    "HttpMethod": "POST",
    "IsController": true,
    "Order": 0,
    "Parameters": [
      {
        "Name": "maSv",
        "Type": "System.String",
        "IsRequired": true
      }
    ],
    "ReturnTypes": []
  },
  {
    "ContainingType": "DiemDanhLopHoc.Controllers.LopHocController",
    "Method": "GetAll",
    "RelativePath": "api/lophoc",
    "HttpMethod": "GET",
    "IsController": true,
    "Order": 0,
    "Parameters": [],
    "ReturnTypes": []
  },
  {
    "ContainingType": "DiemDanhLopHoc.Controllers.LopHocController",
    "Method": "Create",
    "RelativePath": "api/lophoc",
    "HttpMethod": "POST",
    "IsController": true,
    "Order": 0,
    "Parameters": [
      {
        "Name": "request",
        "Type": "DiemDanhLopHoc.DTOs.TaoLopHocDto",
        "IsRequired": true
      }
    ],
    "ReturnTypes": []
  },
  {
    "ContainingType": "DiemDanhLopHoc.Controllers.LopHocController",
    "Method": "AddStudent",
    "RelativePath": "api/lophoc/{maLop}/add-student",
    "HttpMethod": "POST",
    "IsController": true,
    "Order": 0,
    "Parameters": [
      {
        "Name": "maLop",
        "Type": "System.String",
        "IsRequired": true
      },
      {
        "Name": "request",
        "Type": "DiemDanhLopHoc.DTOs.ThemSinhVienRequest",
        "IsRequired": true
      }
    ],
    "ReturnTypes": []
  },
  {
    "ContainingType": "DiemDanhLopHoc.Controllers.LopHocController",
    "Method": "GetStudents",
    "RelativePath": "api/lophoc/{maLop}/students",
    "HttpMethod": "GET",
    "IsController": true,
    "Order": 0,
    "Parameters": [
      {
        "Name": "maLop",
        "Type": "System.String",
        "IsRequired": true
      }
    ],
    "ReturnTypes": []
  },
  {
    "ContainingType": "DiemDanhLopHoc.Controllers.MonHocsController",
    "Method": "GetAll",
    "RelativePath": "api/MonHocs",
    "HttpMethod": "GET",
    "IsController": true,
    "Order": 0,
    "Parameters": [],
    "ReturnTypes": []
  },
  {
    "ContainingType": "DiemDanhLopHoc.Controllers.MonHocsController",
    "Method": "Create",
    "RelativePath": "api/MonHocs",
    "HttpMethod": "POST",
    "IsController": true,
    "Order": 0,
    "Parameters": [
      {
        "Name": "request",
        "Type": "DiemDanhLopHoc.DTOs.MonHocDto",
        "IsRequired": true
      }
    ],
    "ReturnTypes": []
  },
  {
    "ContainingType": "DiemDanhLopHoc.Controllers.MonHocsController",
    "Method": "GetById",
    "RelativePath": "api/MonHocs/{maMon}",
    "HttpMethod": "GET",
    "IsController": true,
    "Order": 0,
    "Parameters": [
      {
        "Name": "maMon",
        "Type": "System.String",
        "IsRequired": true
      }
    ],
    "ReturnTypes": []
  },
  {
    "ContainingType": "DiemDanhLopHoc.Controllers.MonHocsController",
    "Method": "Update",
    "RelativePath": "api/MonHocs/{maMon}",
    "HttpMethod": "PUT",
    "IsController": true,
    "Order": 0,
    "Parameters": [
      {
        "Name": "maMon",
        "Type": "System.String",
        "IsRequired": true
      },
      {
        "Name": "request",
        "Type": "DiemDanhLopHoc.DTOs.MonHocDto",
        "IsRequired": true
      }
    ],
    "ReturnTypes": []
  },
  {
    "ContainingType": "DiemDanhLopHoc.Controllers.MonHocsController",
    "Method": "Delete",
    "RelativePath": "api/MonHocs/{maMon}",
    "HttpMethod": "DELETE",
    "IsController": true,
    "Order": 0,
    "Parameters": [
      {
        "Name": "maMon",
        "Type": "System.String",
        "IsRequired": true
      }
    ],
    "ReturnTypes": []
  },
  {
    "ContainingType": "DiemDanhLopHoc.Controllers.SinhVienController",
    "Method": "GetAll",
    "RelativePath": "api/sinhvien",
    "HttpMethod": "GET",
    "IsController": true,
    "Order": 0,
    "Parameters": [],
    "ReturnTypes": []
  },
  {
    "ContainingType": "DiemDanhLopHoc.Controllers.SinhVienController",
    "Method": "Create",
    "RelativePath": "api/sinhvien",
    "HttpMethod": "POST",
    "IsController": true,
    "Order": 0,
    "Parameters": [
      {
        "Name": "request",
        "Type": "DiemDanhLopHoc.DTOs.TaoSinhVienDto",
        "IsRequired": true
      }
    ],
    "ReturnTypes": []
  },
  {
    "ContainingType": "DiemDanhLopHoc.Controllers.SinhVienController",
    "Method": "Update",
    "RelativePath": "api/sinhvien/{maSv}",
    "HttpMethod": "PUT",
    "IsController": true,
    "Order": 0,
    "Parameters": [
      {
        "Name": "maSv",
        "Type": "System.String",
        "IsRequired": true
      },
      {
        "Name": "request",
        "Type": "DiemDanhLopHoc.DTOs.CapNhatSinhVienDto",
        "IsRequired": true
      }
    ],
    "ReturnTypes": []
  },
  {
    "ContainingType": "DiemDanhLopHoc.Controllers.SinhVienController",
    "Method": "Delete",
    "RelativePath": "api/sinhvien/{maSv}",
    "HttpMethod": "DELETE",
    "IsController": true,
    "Order": 0,
    "Parameters": [
      {
        "Name": "maSv",
        "Type": "System.String",
        "IsRequired": true
      }
    ],
    "ReturnTypes": []
  },
  {
    "ContainingType": "DiemDanhLopHoc.Controllers.SinhVienController",
    "Method": "ImportExcel",
    "RelativePath": "api/sinhvien/import",
    "HttpMethod": "POST",
    "IsController": true,
    "Order": 0,
    "Parameters": [
      {
        "Name": "requests",
        "Type": "System.Collections.Generic.List\u00601[[DiemDanhLopHoc.DTOs.TaoSinhVienDto, DiemDanhLopHoc, Version=1.0.0.0, Culture=neutral, PublicKeyToken=null]]",
        "IsRequired": true
      }
    ],
    "ReturnTypes": []
  }
]